AUTHORS
MANIFEST.in
README.rst
setup.py
cmsplugin_nivoslider/__init__.py
cmsplugin_nivoslider/cms_plugins.py
cmsplugin_nivoslider/models.py
cmsplugin_nivoslider/thumbnail_processors.py
cmsplugin_nivoslider.egg-info/PKG-INFO
cmsplugin_nivoslider.egg-info/SOURCES.txt
cmsplugin_nivoslider.egg-info/dependency_links.txt
cmsplugin_nivoslider.egg-info/not-zip-safe
cmsplugin_nivoslider.egg-info/requires.txt
cmsplugin_nivoslider.egg-info/top_level.txt
cmsplugin_nivoslider/locale/en/LC_MESSAGES/django.mo
cmsplugin_nivoslider/locale/en/LC_MESSAGES/django.po
cmsplugin_nivoslider/locale/fr/LC_MESSAGES/django.mo
cmsplugin_nivoslider/locale/fr/LC_MESSAGES/django.po
cmsplugin_nivoslider/migrations/0001_initial.py
cmsplugin_nivoslider/migrations/__init__.py
cmsplugin_nivoslider/south_migrations/0001_initial.py
cmsplugin_nivoslider/south_migrations/0002_auto__add_field_sliderplugin_theme__add_field_sliderplugin_effect.py
cmsplugin_nivoslider/south_migrations/0003_auto__add_field_sliderplugin_anim_speed__add_field_sliderplugin_pause_.py
cmsplugin_nivoslider/south_migrations/0004_auto__add_field_sliderplugin_image_width__add_field_sliderplugin_image.py
cmsplugin_nivoslider/south_migrations/0005_auto__add_field_sliderplugin_show_ribbon.py
cmsplugin_nivoslider/south_migrations/0006_rename_fields_image_height_width__del_field_show_ribbon.py
cmsplugin_nivoslider/south_migrations/0007_auto__add_field_sliderplugin_manual_advance__add_field_sliderplugin_ar.py
cmsplugin_nivoslider/south_migrations/0008_auto__del_sliderimage__del_slideralbum.py
cmsplugin_nivoslider/south_migrations/0009_rename_table.py
cmsplugin_nivoslider/south_migrations/__init__.py
cmsplugin_nivoslider/static/nivo/nivo-slider.css
cmsplugin_nivoslider/static/nivo/js/jquery.nivo.slider.pack.js
cmsplugin_nivoslider/static/nivo/themes/bar/arrows.png
cmsplugin_nivoslider/static/nivo/themes/bar/bar.css
cmsplugin_nivoslider/static/nivo/themes/bar/bullets.png
cmsplugin_nivoslider/static/nivo/themes/bar/loading.gif
cmsplugin_nivoslider/static/nivo/themes/dark/arrows.png
cmsplugin_nivoslider/static/nivo/themes/dark/bullets.png
cmsplugin_nivoslider/static/nivo/themes/dark/dark.css
cmsplugin_nivoslider/static/nivo/themes/dark/loading.gif
