Metadata-Version: 1.1
Name: cmsplugin-nivoslider
Version: 0.5.8
Summary: Simple Nivo Slider plugin for django-cms
Home-page: https://bitbucket.org/bercab/cmsplugin-nivoslider
Author: Bernardo Cabezas Serra / apsl.net, Bertrand Bordage, Marion Balensi, Marc DM, 
Author-email: bcabezas@apsl.net
License: MIT
Platform: UNKNOWN
Classifier: Development Status :: 5 - Production/Stable
Classifier: Framework :: Django
Classifier: Intended Audience :: Developers
Classifier: License :: OSI Approved :: MIT License
Classifier: Operating System :: OS Independent
Classifier: Programming Language :: Python
Classifier: Topic :: Internet :: WWW/HTTP
